{"metaInfo":{"dataIndex":"entityData","collectionName":"entities","responseObjectName":"response"},"entities":[{"id":"BOOTCUT_stcomplegstylevalues","name":"BOOTCUT","type":"stcomplegstylevalues","domain":"referenceData","properties":{"source":"internal","modifiedByService":"entityservice","modifiedBy":"initLoad","modifiedDate":"6/1/2017  00:00:00 AM"},"data":{"attributes":{"referencedatacode":{"values":[{"value":"BOOTCUT","source":"internal","locale":"en-US"}]},"referencedatavalue":{"values":[{"value":"BOOTCUT","source":"internal","locale":"en-US"}]},"externalName":{"values":[{"value":"BOOTCUT","source":"internal","locale":"en-US"}]}}}},{"id":"CUFFED_stcomplegstylevalues","name":"CUFFED","type":"stcomplegstylevalues","domain":"referenceData","properties":{"source":"internal","modifiedByService":"entityservice","modifiedBy":"initLoad","modifiedDate":"6/1/2017  00:00:00 AM"},"data":{"attributes":{"referencedatacode":{"values":[{"value":"CUFFED","source":"internal","locale":"en-US"}]},"referencedatavalue":{"values":[{"value":"CUFFED","source":"internal","locale":"en-US"}]},"externalName":{"values":[{"value":"CUFFED","source":"internal","locale":"en-US"}]}}}},{"id":"CUFFED_LEG_stcomplegstylevalues","name":"CUFFED_LEG","type":"stcomplegstylevalues","domain":"referenceData","properties":{"source":"internal","modifiedByService":"entityservice","modifiedBy":"initLoad","modifiedDate":"6/1/2017  00:00:00 AM"},"data":{"attributes":{"referencedatacode":{"values":[{"value":"CUFFED_LEG","source":"internal","locale":"en-US"}]},"referencedatavalue":{"values":[{"value":"CUFFED LEG","source":"internal","locale":"en-US"}]},"externalName":{"values":[{"value":"CUFFED LEG","source":"internal","locale":"en-US"}]}}}},{"id":"FLARE_stcomplegstylevalues","name":"FLARE","type":"stcomplegstylevalues","domain":"referenceData","properties":{"source":"internal","modifiedByService":"entityservice","modifiedBy":"initLoad","modifiedDate":"6/1/2017  00:00:00 AM"},"data":{"attributes":{"referencedatacode":{"values":[{"value":"FLARE","source":"internal","locale":"en-US"}]},"referencedatavalue":{"values":[{"value":"FLARE","source":"internal","locale":"en-US"}]},"externalName":{"values":[{"value":"FLARE","source":"internal","locale":"en-US"}]}}}},{"id":"FLARE_LEG_stcomplegstylevalues","name":"FLARE_LEG","type":"stcomplegstylevalues","domain":"referenceData","properties":{"source":"internal","modifiedByService":"entityservice","modifiedBy":"initLoad","modifiedDate":"6/1/2017  00:00:00 AM"},"data":{"attributes":{"referencedatacode":{"values":[{"value":"FLARE_LEG","source":"internal","locale":"en-US"}]},"referencedatavalue":{"values":[{"value":"FLARE LEG","source":"internal","locale":"en-US"}]},"externalName":{"values":[{"value":"FLARE LEG","source":"internal","locale":"en-US"}]}}}},{"id":"HEMMED_stcomplegstylevalues","name":"HEMMED","type":"stcomplegstylevalues","domain":"referenceData","properties":{"source":"internal","modifiedByService":"entityservice","modifiedBy":"initLoad","modifiedDate":"6/1/2017  00:00:00 AM"},"data":{"attributes":{"referencedatacode":{"values":[{"value":"HEMMED","source":"internal","locale":"en-US"}]},"referencedatavalue":{"values":[{"value":"HEMMED","source":"internal","locale":"en-US"}]},"externalName":{"values":[{"value":"HEMMED","source":"internal","locale":"en-US"}]}}}},{"id":"NOT_APPLICABLE_stcomplegstylevalues","name":"NOT_APPLICABLE","type":"stcomplegstylevalues","domain":"referenceData","properties":{"source":"internal","modifiedByService":"entityservice","modifiedBy":"initLoad","modifiedDate":"6/1/2017  00:00:00 AM"},"data":{"attributes":{"referencedatacode":{"values":[{"value":"NOT_APPLICABLE","source":"internal","locale":"en-US"}]},"referencedatavalue":{"values":[{"value":"NOT APPLICABLE","source":"internal","locale":"en-US"}]},"externalName":{"values":[{"value":"NOT APPLICABLE","source":"internal","locale":"en-US"}]}}}},{"id":"OTHER_stcomplegstylevalues","name":"OTHER","type":"stcomplegstylevalues","domain":"referenceData","properties":{"source":"internal","modifiedByService":"entityservice","modifiedBy":"initLoad","modifiedDate":"6/1/2017  00:00:00 AM"},"data":{"attributes":{"referencedatacode":{"values":[{"value":"OTHER","source":"internal","locale":"en-US"}]},"referencedatavalue":{"values":[{"value":"OTHER","source":"internal","locale":"en-US"}]},"externalName":{"values":[{"value":"OTHER","source":"internal","locale":"en-US"}]}}}},{"id":"SKINNY_stcomplegstylevalues","name":"SKINNY","type":"stcomplegstylevalues","domain":"referenceData","properties":{"source":"internal","modifiedByService":"entityservice","modifiedBy":"initLoad","modifiedDate":"6/1/2017  00:00:00 AM"},"data":{"attributes":{"referencedatacode":{"values":[{"value":"SKINNY","source":"internal","locale":"en-US"}]},"referencedatavalue":{"values":[{"value":"SKINNY","source":"internal","locale":"en-US"}]},"externalName":{"values":[{"value":"SKINNY","source":"internal","locale":"en-US"}]}}}},{"id":"SKINNY_LEG_stcomplegstylevalues","name":"SKINNY_LEG","type":"stcomplegstylevalues","domain":"referenceData","properties":{"source":"internal","modifiedByService":"entityservice","modifiedBy":"initLoad","modifiedDate":"6/1/2017  00:00:00 AM"},"data":{"attributes":{"referencedatacode":{"values":[{"value":"SKINNY_LEG","source":"internal","locale":"en-US"}]},"referencedatavalue":{"values":[{"value":"SKINNY LEG","source":"internal","locale":"en-US"}]},"externalName":{"values":[{"value":"SKINNY LEG","source":"internal","locale":"en-US"}]}}}},{"id":"SLIM_LEG_stcomplegstylevalues","name":"SLIM_LEG","type":"stcomplegstylevalues","domain":"referenceData","properties":{"source":"internal","modifiedByService":"entityservice","modifiedBy":"initLoad","modifiedDate":"6/1/2017  00:00:00 AM"},"data":{"attributes":{"referencedatacode":{"values":[{"value":"SLIM_LEG","source":"internal","locale":"en-US"}]},"referencedatavalue":{"values":[{"value":"SLIM LEG","source":"internal","locale":"en-US"}]},"externalName":{"values":[{"value":"SLIM LEG","source":"internal","locale":"en-US"}]}}}},{"id":"SNEAKER_CUT_stcomplegstylevalues","name":"SNEAKER_CUT","type":"stcomplegstylevalues","domain":"referenceData","properties":{"source":"internal","modifiedByService":"entityservice","modifiedBy":"initLoad","modifiedDate":"6/1/2017  00:00:00 AM"},"data":{"attributes":{"referencedatacode":{"values":[{"value":"SNEAKER_CUT","source":"internal","locale":"en-US"}]},"referencedatavalue":{"values":[{"value":"SNEAKER CUT","source":"internal","locale":"en-US"}]},"externalName":{"values":[{"value":"SNEAKER CUT","source":"internal","locale":"en-US"}]}}}},{"id":"STRAIGHT_stcomplegstylevalues","name":"STRAIGHT","type":"stcomplegstylevalues","domain":"referenceData","properties":{"source":"internal","modifiedByService":"entityservice","modifiedBy":"initLoad","modifiedDate":"6/1/2017  00:00:00 AM"},"data":{"attributes":{"referencedatacode":{"values":[{"value":"STRAIGHT","source":"internal","locale":"en-US"}]},"referencedatavalue":{"values":[{"value":"STRAIGHT","source":"internal","locale":"en-US"}]},"externalName":{"values":[{"value":"STRAIGHT","source":"internal","locale":"en-US"}]}}}},{"id":"STRAIGHT_LEG_stcomplegstylevalues","name":"STRAIGHT_LEG","type":"stcomplegstylevalues","domain":"referenceData","properties":{"source":"internal","modifiedByService":"entityservice","modifiedBy":"initLoad","modifiedDate":"6/1/2017  00:00:00 AM"},"data":{"attributes":{"referencedatacode":{"values":[{"value":"STRAIGHT_LEG","source":"internal","locale":"en-US"}]},"referencedatavalue":{"values":[{"value":"STRAIGHT LEG","source":"internal","locale":"en-US"}]},"externalName":{"values":[{"value":"STRAIGHT LEG","source":"internal","locale":"en-US"}]}}}},{"id":"TAPERED_stcomplegstylevalues","name":"TAPERED","type":"stcomplegstylevalues","domain":"referenceData","properties":{"source":"internal","modifiedByService":"entityservice","modifiedBy":"initLoad","modifiedDate":"6/1/2017  00:00:00 AM"},"data":{"attributes":{"referencedatacode":{"values":[{"value":"TAPERED","source":"internal","locale":"en-US"}]},"referencedatavalue":{"values":[{"value":"TAPERED","source":"internal","locale":"en-US"}]},"externalName":{"values":[{"value":"TAPERED","source":"internal","locale":"en-US"}]}}}},{"id":"TAPERED_LEG_stcomplegstylevalues","name":"TAPERED_LEG","type":"stcomplegstylevalues","domain":"referenceData","properties":{"source":"internal","modifiedByService":"entityservice","modifiedBy":"initLoad","modifiedDate":"6/1/2017  00:00:00 AM"},"data":{"attributes":{"referencedatacode":{"values":[{"value":"TAPERED_LEG","source":"internal","locale":"en-US"}]},"referencedatavalue":{"values":[{"value":"TAPERED LEG","source":"internal","locale":"en-US"}]},"externalName":{"values":[{"value":"TAPERED LEG","source":"internal","locale":"en-US"}]}}}},{"id":"UNFINISHED_stcomplegstylevalues","name":"UNFINISHED","type":"stcomplegstylevalues","domain":"referenceData","properties":{"source":"internal","modifiedByService":"entityservice","modifiedBy":"initLoad","modifiedDate":"6/1/2017  00:00:00 AM"},"data":{"attributes":{"referencedatacode":{"values":[{"value":"UNFINISHED","source":"internal","locale":"en-US"}]},"referencedatavalue":{"values":[{"value":"UNFINISHED","source":"internal","locale":"en-US"}]},"externalName":{"values":[{"value":"UNFINISHED","source":"internal","locale":"en-US"}]}}}},{"id":"WIDE_stcomplegstylevalues","name":"WIDE","type":"stcomplegstylevalues","domain":"referenceData","properties":{"source":"internal","modifiedByService":"entityservice","modifiedBy":"initLoad","modifiedDate":"6/1/2017  00:00:00 AM"},"data":{"attributes":{"referencedatacode":{"values":[{"value":"WIDE","source":"internal","locale":"en-US"}]},"referencedatavalue":{"values":[{"value":"WIDE","source":"internal","locale":"en-US"}]},"externalName":{"values":[{"value":"WIDE","source":"internal","locale":"en-US"}]}}}},{"id":"WIDE_LEG_stcomplegstylevalues","name":"WIDE_LEG","type":"stcomplegstylevalues","domain":"referenceData","properties":{"source":"internal","modifiedByService":"entityservice","modifiedBy":"initLoad","modifiedDate":"6/1/2017  00:00:00 AM"},"data":{"attributes":{"referencedatacode":{"values":[{"value":"WIDE_LEG","source":"internal","locale":"en-US"}]},"referencedatavalue":{"values":[{"value":"WIDE LEG","source":"internal","locale":"en-US"}]},"externalName":{"values":[{"value":"WIDE LEG","source":"internal","locale":"en-US"}]}}}}]}