{"metaInfo":{"dataIndex":"entityData","collectionName":"entities","responseObjectName":"response"},"entities":[{"id":"","name":"1 DUPLEX OUTLET COVER","type":"configurationvalues","domain":"referenceData","data":{"attributes":{"referencedatacode":{"values":[{"value":"1_DUPLEX_OUTLET_COVE","source":"internal","locale":"en-US"}]},"referencedatavalue":{"values":[{"value":"1 DUPLEX OUTLET COVER","source":"internal","locale":"en-US"}]}}}},{"id":"","name":"1 OUTLET","type":"configurationvalues","domain":"referenceData","data":{"attributes":{"referencedatacode":{"values":[{"value":"1_OUTLET","source":"internal","locale":"en-US"}]},"referencedatavalue":{"values":[{"value":"1 OUTLET","source":"internal","locale":"en-US"}]}}}},{"id":"","name":"1 PORT","type":"configurationvalues","domain":"referenceData","data":{"attributes":{"referencedatacode":{"values":[{"value":"1_PORT","source":"internal","locale":"en-US"}]},"referencedatavalue":{"values":[{"value":"1 PORT","source":"internal","locale":"en-US"}]}}}},{"id":"","name":"1 PULL CHAIN SWITCH","type":"configurationvalues","domain":"referenceData","data":{"attributes":{"referencedatacode":{"values":[{"value":"1_PULL_CHAIN_SWITCH","source":"internal","locale":"en-US"}]},"referencedatavalue":{"values":[{"value":"1 PULL CHAIN SWITCH","source":"internal","locale":"en-US"}]}}}},{"id":"","name":"1 PUSH BUTTON SWITCH","type":"configurationvalues","domain":"referenceData","data":{"attributes":{"referencedatacode":{"values":[{"value":"1_PUSH_BUTTON_SWITCH","source":"internal","locale":"en-US"}]},"referencedatavalue":{"values":[{"value":"1 PUSH BUTTON SWITCH","source":"internal","locale":"en-US"}]}}}},{"id":"","name":"1 ROCKER","type":"configurationvalues","domain":"referenceData","data":{"attributes":{"referencedatacode":{"values":[{"value":"1_ROCKER","source":"internal","locale":"en-US"}]},"referencedatavalue":{"values":[{"value":"1 ROCKER","source":"internal","locale":"en-US"}]}}}},{"id":"","name":"1 ROTARY SWITCH","type":"configurationvalues","domain":"referenceData","data":{"attributes":{"referencedatacode":{"values":[{"value":"1_ROTARY_SWITCH","source":"internal","locale":"en-US"}]},"referencedatavalue":{"values":[{"value":"1 ROTARY SWITCH","source":"internal","locale":"en-US"}]}}}},{"id":"","name":"1 THUMB WHEEL CORD SWITCH","type":"configurationvalues","domain":"referenceData","data":{"attributes":{"referencedatacode":{"values":[{"value":"1_THUMB_WHEEL_CORD_S","source":"internal","locale":"en-US"}]},"referencedatavalue":{"values":[{"value":"1 THUMB WHEEL CORD SWITCH","source":"internal","locale":"en-US"}]}}}},{"id":"","name":"1 TIMER SWITCH","type":"configurationvalues","domain":"referenceData","data":{"attributes":{"referencedatacode":{"values":[{"value":"1_TIMER_SWITCH","source":"internal","locale":"en-US"}]},"referencedatavalue":{"values":[{"value":"1 TIMER SWITCH","source":"internal","locale":"en-US"}]}}}},{"id":"","name":"1 TOGGLE","type":"configurationvalues","domain":"referenceData","data":{"attributes":{"referencedatacode":{"values":[{"value":"1_TOGGLE","source":"internal","locale":"en-US"}]},"referencedatavalue":{"values":[{"value":"1 TOGGLE","source":"internal","locale":"en-US"}]}}}},{"id":"","name":"2 DUPLEX OUTLET COVER","type":"configurationvalues","domain":"referenceData","data":{"attributes":{"referencedatacode":{"values":[{"value":"2_DUPLEX_OUTLET_COVE","source":"internal","locale":"en-US"}]},"referencedatavalue":{"values":[{"value":"2 DUPLEX OUTLET COVER","source":"internal","locale":"en-US"}]}}}},{"id":"","name":"2 OUTLET","type":"configurationvalues","domain":"referenceData","data":{"attributes":{"referencedatacode":{"values":[{"value":"2_OUTLET","source":"internal","locale":"en-US"}]},"referencedatavalue":{"values":[{"value":"2 OUTLET","source":"internal","locale":"en-US"}]}}}},{"id":"","name":"2 PORT","type":"configurationvalues","domain":"referenceData","data":{"attributes":{"referencedatacode":{"values":[{"value":"2_PORT","source":"internal","locale":"en-US"}]},"referencedatavalue":{"values":[{"value":"2 PORT","source":"internal","locale":"en-US"}]}}}},{"id":"","name":"2 ROCKER","type":"configurationvalues","domain":"referenceData","data":{"attributes":{"referencedatacode":{"values":[{"value":"2_ROCKER","source":"internal","locale":"en-US"}]},"referencedatavalue":{"values":[{"value":"2 ROCKER","source":"internal","locale":"en-US"}]}}}},{"id":"","name":"2 TOGGLE","type":"configurationvalues","domain":"referenceData","data":{"attributes":{"referencedatacode":{"values":[{"value":"2_TOGGLE","source":"internal","locale":"en-US"}]},"referencedatavalue":{"values":[{"value":"2 TOGGLE","source":"internal","locale":"en-US"}]}}}},{"id":"","name":"2 USB CHARGING PORT","type":"configurationvalues","domain":"referenceData","data":{"attributes":{"referencedatacode":{"values":[{"value":"2_USB_CHARGING_PORT","source":"internal","locale":"en-US"}]},"referencedatavalue":{"values":[{"value":"2 USB CHARGING PORT","source":"internal","locale":"en-US"}]}}}},{"id":"","name":"3 OUTLET","type":"configurationvalues","domain":"referenceData","data":{"attributes":{"referencedatacode":{"values":[{"value":"3_OUTLET","source":"internal","locale":"en-US"}]},"referencedatavalue":{"values":[{"value":"3 OUTLET","source":"internal","locale":"en-US"}]}}}},{"id":"","name":"3 PORT","type":"configurationvalues","domain":"referenceData","data":{"attributes":{"referencedatacode":{"values":[{"value":"3_PORT","source":"internal","locale":"en-US"}]},"referencedatavalue":{"values":[{"value":"3 PORT","source":"internal","locale":"en-US"}]}}}},{"id":"","name":"3 ROCKER","type":"configurationvalues","domain":"referenceData","data":{"attributes":{"referencedatacode":{"values":[{"value":"3_ROCKER","source":"internal","locale":"en-US"}]},"referencedatavalue":{"values":[{"value":"3 ROCKER","source":"internal","locale":"en-US"}]}}}},{"id":"","name":"3 TOGGLE","type":"configurationvalues","domain":"referenceData","data":{"attributes":{"referencedatacode":{"values":[{"value":"3_TOGGLE","source":"internal","locale":"en-US"}]},"referencedatavalue":{"values":[{"value":"3 TOGGLE","source":"internal","locale":"en-US"}]}}}},{"id":"","name":"4 OUTLET","type":"configurationvalues","domain":"referenceData","data":{"attributes":{"referencedatacode":{"values":[{"value":"4_OUTLET","source":"internal","locale":"en-US"}]},"referencedatavalue":{"values":[{"value":"4 OUTLET","source":"internal","locale":"en-US"}]}}}},{"id":"","name":"4 PORT","type":"configurationvalues","domain":"referenceData","data":{"attributes":{"referencedatacode":{"values":[{"value":"4_PORT","source":"internal","locale":"en-US"}]},"referencedatavalue":{"values":[{"value":"4 PORT","source":"internal","locale":"en-US"}]}}}},{"id":"","name":"4 ROCKER","type":"configurationvalues","domain":"referenceData","data":{"attributes":{"referencedatacode":{"values":[{"value":"4_ROCKER","source":"internal","locale":"en-US"}]},"referencedatavalue":{"values":[{"value":"4 ROCKER","source":"internal","locale":"en-US"}]}}}},{"id":"","name":"4 TOGGLE","type":"configurationvalues","domain":"referenceData","data":{"attributes":{"referencedatacode":{"values":[{"value":"4_TOGGLE","source":"internal","locale":"en-US"}]},"referencedatavalue":{"values":[{"value":"4 TOGGLE","source":"internal","locale":"en-US"}]}}}},{"id":"","name":"5 OUTLET","type":"configurationvalues","domain":"referenceData","data":{"attributes":{"referencedatacode":{"values":[{"value":"5_OUTLET","source":"internal","locale":"en-US"}]},"referencedatavalue":{"values":[{"value":"5 OUTLET","source":"internal","locale":"en-US"}]}}}},{"id":"","name":"5 PORT","type":"configurationvalues","domain":"referenceData","data":{"attributes":{"referencedatacode":{"values":[{"value":"5_PORT","source":"internal","locale":"en-US"}]},"referencedatavalue":{"values":[{"value":"5 PORT","source":"internal","locale":"en-US"}]}}}},{"id":"","name":"5 ROCKER","type":"configurationvalues","domain":"referenceData","data":{"attributes":{"referencedatacode":{"values":[{"value":"5_ROCKER","source":"internal","locale":"en-US"}]},"referencedatavalue":{"values":[{"value":"5 ROCKER","source":"internal","locale":"en-US"}]}}}},{"id":"","name":"5 TOGGLE","type":"configurationvalues","domain":"referenceData","data":{"attributes":{"referencedatacode":{"values":[{"value":"5_TOGGLE","source":"internal","locale":"en-US"}]},"referencedatavalue":{"values":[{"value":"5 TOGGLE","source":"internal","locale":"en-US"}]}}}},{"id":"","name":"6 OUTLET","type":"configurationvalues","domain":"referenceData","data":{"attributes":{"referencedatacode":{"values":[{"value":"6_OUTLET","source":"internal","locale":"en-US"}]},"referencedatavalue":{"values":[{"value":"6 OUTLET","source":"internal","locale":"en-US"}]}}}},{"id":"","name":"6 PORT","type":"configurationvalues","domain":"referenceData","data":{"attributes":{"referencedatacode":{"values":[{"value":"6_PORT","source":"internal","locale":"en-US"}]},"referencedatavalue":{"values":[{"value":"6 PORT","source":"internal","locale":"en-US"}]}}}},{"id":"","name":"7 OUTLET","type":"configurationvalues","domain":"referenceData","data":{"attributes":{"referencedatacode":{"values":[{"value":"7_OUTLET","source":"internal","locale":"en-US"}]},"referencedatavalue":{"values":[{"value":"7 OUTLET","source":"internal","locale":"en-US"}]}}}},{"id":"","name":"AUDIO JACK","type":"configurationvalues","domain":"referenceData","data":{"attributes":{"referencedatacode":{"values":[{"value":"AUDIO_JACK","source":"internal","locale":"en-US"}]},"referencedatavalue":{"values":[{"value":"AUDIO JACK","source":"internal","locale":"en-US"}]}}}},{"id":"","name":"BRUSH PLATE","type":"configurationvalues","domain":"referenceData","data":{"attributes":{"referencedatacode":{"values":[{"value":"BRUSH_PLATE","source":"internal","locale":"en-US"}]},"referencedatavalue":{"values":[{"value":"BRUSH PLATE","source":"internal","locale":"en-US"}]}}}},{"id":"","name":"CAT5E ETHERNET JACK","type":"configurationvalues","domain":"referenceData","data":{"attributes":{"referencedatacode":{"values":[{"value":"CAT5E ETHERNET_JACK","source":"internal","locale":"en-US"}]},"referencedatavalue":{"values":[{"value":"CAT5E ETHERNET JACK","source":"internal","locale":"en-US"}]}}}},{"id":"","name":"CAT6  ETHERNET JACK","type":"configurationvalues","domain":"referenceData","data":{"attributes":{"referencedatacode":{"values":[{"value":"CAT6 _ETHERNET_JACK","source":"internal","locale":"en-US"}]},"referencedatavalue":{"values":[{"value":"CAT6  ETHERNET JACK","source":"internal","locale":"en-US"}]}}}},{"id":"","name":"COAXIAL JACK","type":"configurationvalues","domain":"referenceData","data":{"attributes":{"referencedatacode":{"values":[{"value":"COAXIAL_JACK","source":"internal","locale":"en-US"}]},"referencedatavalue":{"values":[{"value":"COAXIAL JACK","source":"internal","locale":"en-US"}]}}}},{"id":"","name":"DATA JACK","type":"configurationvalues","domain":"referenceData","data":{"attributes":{"referencedatacode":{"values":[{"value":"DATA_JACK","source":"internal","locale":"en-US"}]},"referencedatavalue":{"values":[{"value":"DATA JACK","source":"internal","locale":"en-US"}]}}}},{"id":"","name":"HDMI JACK","type":"configurationvalues","domain":"referenceData","data":{"attributes":{"referencedatacode":{"values":[{"value":"HDMI_JACK","source":"internal","locale":"en-US"}]},"referencedatavalue":{"values":[{"value":"HDMI JACK","source":"internal","locale":"en-US"}]}}}},{"id":"","name":"NOT APPLICABLE","type":"configurationvalues","domain":"referenceData","data":{"attributes":{"referencedatacode":{"values":[{"value":"NOT_APPLICABLE","source":"internal","locale":"en-US"}]},"referencedatavalue":{"values":[{"value":"NOT APPLICABLE","source":"internal","locale":"en-US"}]}}}},{"id":"","name":"PHONE JACK","type":"configurationvalues","domain":"referenceData","data":{"attributes":{"referencedatacode":{"values":[{"value":"PHONE_JACK","source":"internal","locale":"en-US"}]},"referencedatavalue":{"values":[{"value":"PHONE JACK","source":"internal","locale":"en-US"}]}}}},{"id":"","name":"RJ45 ETHERNET JACK","type":"configurationvalues","domain":"referenceData","data":{"attributes":{"referencedatacode":{"values":[{"value":"RJ45_ETHERNET_JACK","source":"internal","locale":"en-US"}]},"referencedatavalue":{"values":[{"value":"RJ45 ETHERNET JACK","source":"internal","locale":"en-US"}]}}}},{"id":"","name":"USB CHARGING PORT","type":"configurationvalues","domain":"referenceData","data":{"attributes":{"referencedatacode":{"values":[{"value":"USB_CHARGING_PORT","source":"internal","locale":"en-US"}]},"referencedatavalue":{"values":[{"value":"USB CHARGING PORT","source":"internal","locale":"en-US"}]}}}},{"id":"","name":"VIDEO JACK","type":"configurationvalues","domain":"referenceData","data":{"attributes":{"referencedatacode":{"values":[{"value":"VIDEO_JACK","source":"internal","locale":"en-US"}]},"referencedatavalue":{"values":[{"value":"VIDEO JACK","source":"internal","locale":"en-US"}]}}}}]}