{"metaInfo":{"dataIndex":"entityData","collectionName":"entities","responseObjectName":"response"},"entities":[{"id":"","name":"30 PINTS PER DAY","type":"moistureremovalcapvalues","domain":"referenceData","data":{"attributes":{"referencedatacode":{"values":[{"value":"30_PINTS_PER_DAY","source":"internal","locale":"en-US"}]},"referencedatavalue":{"values":[{"value":"30 PINTS PER DAY","source":"internal","locale":"en-US"}]}}}},{"id":"","name":"50 PINTS PER DAY","type":"moistureremovalcapvalues","domain":"referenceData","data":{"attributes":{"referencedatacode":{"values":[{"value":"50_PINTS_PER_DAY","source":"internal","locale":"en-US"}]},"referencedatavalue":{"values":[{"value":"50 PINTS PER DAY","source":"internal","locale":"en-US"}]}}}},{"id":"","name":"65 PINTS PER DAY","type":"moistureremovalcapvalues","domain":"referenceData","data":{"attributes":{"referencedatacode":{"values":[{"value":"65_PINTS_PER_DAY","source":"internal","locale":"en-US"}]},"referencedatavalue":{"values":[{"value":"65 PINTS PER DAY","source":"internal","locale":"en-US"}]}}}},{"id":"","name":"70 PINTS PER DAY","type":"moistureremovalcapvalues","domain":"referenceData","data":{"attributes":{"referencedatacode":{"values":[{"value":"70_PINTS_PER_DAY","source":"internal","locale":"en-US"}]},"referencedatavalue":{"values":[{"value":"70 PINTS PER DAY","source":"internal","locale":"en-US"}]}}}},{"id":"","name":"90 PINTS PER DAY","type":"moistureremovalcapvalues","domain":"referenceData","data":{"attributes":{"referencedatacode":{"values":[{"value":"90_PINTS_PER_DAY","source":"internal","locale":"en-US"}]},"referencedatavalue":{"values":[{"value":"90 PINTS PER DAY","source":"internal","locale":"en-US"}]}}}},{"id":"","name":"NOT APPLICABLE","type":"moistureremovalcapvalues","domain":"referenceData","data":{"attributes":{"referencedatacode":{"values":[{"value":"NOT_APPLICABLE","source":"internal","locale":"en-US"}]},"referencedatavalue":{"values":[{"value":"NOT APPLICABLE","source":"internal","locale":"en-US"}]}}}}]}