{"metaInfo":{"dataIndex":"entityData","collectionName":"entities","responseObjectName":"response"},"entities":[{"id":"elasticanchorbands_mattresssecuringvalues","name":"ELASTIC_ANCHOR_BANDS","type":"mattresssecuringvalues","domain":"referenceData","properties":{"source":"internal"},"data":{"attributes":{"referencedatacode":{"values":[{"value":"ELASTIC_ANCHOR_BANDS","source":"internal","locale":"eng_us"}]},"referencedatavalue":{"values":[{"value":"ELASTIC ANCHOR BANDS","source":"internal","locale":"eng_us"}]},"externalName":{"values":[{"value":"ELASTIC ANCHOR BANDS","source":"internal","locale":"eng_us"}]}}}},{"id":"notapplicable_mattresssecuringvalues","name":"NOT_APPLICABLE","type":"mattresssecuringvalues","domain":"referenceData","properties":{"source":"internal"},"data":{"attributes":{"referencedatacode":{"values":[{"value":"NOT_APPLICABLE","source":"internal","locale":"eng_us"}]},"referencedatavalue":{"values":[{"value":"NOT APPLICABLE","source":"internal","locale":"eng_us"}]},"externalName":{"values":[{"value":"NOT APPLICABLE","source":"internal","locale":"eng_us"}]}}}},{"id":"nosecuremechanism_mattresssecuringvalues","name":"NO_SECURE_MECHANISM","type":"mattresssecuringvalues","domain":"referenceData","properties":{"source":"internal"},"data":{"attributes":{"referencedatacode":{"values":[{"value":"NO_SECURE_MECHANISM","source":"internal","locale":"eng_us"}]},"referencedatavalue":{"values":[{"value":"NO SECURE MECHANISM","source":"internal","locale":"eng_us"}]},"externalName":{"values":[{"value":"NO SECURE MECHANISM","source":"internal","locale":"eng_us"}]}}}},{"id":"skirt_mattresssecuringvalues","name":"SKIRT","type":"mattresssecuringvalues","domain":"referenceData","properties":{"source":"internal"},"data":{"attributes":{"referencedatacode":{"values":[{"value":"SKIRT","source":"internal","locale":"eng_us"}]},"referencedatavalue":{"values":[{"value":"SKIRT","source":"internal","locale":"eng_us"}]},"externalName":{"values":[{"value":"SKIRT","source":"internal","locale":"eng_us"}]}}}},{"id":"staymadecorners_mattresssecuringvalues","name":"STAY_MADE_CORNERS","type":"mattresssecuringvalues","domain":"referenceData","properties":{"source":"internal"},"data":{"attributes":{"referencedatacode":{"values":[{"value":"STAY_MADE_CORNERS","source":"internal","locale":"eng_us"}]},"referencedatavalue":{"values":[{"value":"STAY MADE CORNERS","source":"internal","locale":"eng_us"}]},"externalName":{"values":[{"value":"STAY MADE CORNERS","source":"internal","locale":"eng_us"}]}}}}]}