{"metaInfo":{"dataIndex":"entityData","collectionName":"entities","responseObjectName":"response"},"entities":[{"id":"amorillion_stonecutvalues","name":"AMORILLION","type":"stonecutvalues","domain":"referenceData","properties":{"source":"internal"},"data":{"attributes":{"referencedatacode":{"values":[{"value":"AMORILLION","source":"internal","locale":"en-US"}]},"referencedatavalue":{"values":[{"value":"AMORILLION","source":"internal","locale":"en-US"}]},"externalName":{"values":[{"value":"AMORILLION","source":"internal","locale":"en-US"}]}}}},{"id":"asscher_stonecutvalues","name":"ASSCHER","type":"stonecutvalues","domain":"referenceData","properties":{"source":"internal"},"data":{"attributes":{"referencedatacode":{"values":[{"value":"ASSCHER","source":"internal","locale":"en-US"}]},"referencedatavalue":{"values":[{"value":"ASSCHER","source":"internal","locale":"en-US"}]},"externalName":{"values":[{"value":"ASSCHER","source":"internal","locale":"en-US"}]}}}},{"id":"baguette_stonecutvalues","name":"BAGUETTE","type":"stonecutvalues","domain":"referenceData","properties":{"source":"internal"},"data":{"attributes":{"referencedatacode":{"values":[{"value":"BAGUETTE","source":"internal","locale":"en-US"}]},"referencedatavalue":{"values":[{"value":"BAGUETTE","source":"internal","locale":"en-US"}]},"externalName":{"values":[{"value":"BAGUETTE","source":"internal","locale":"en-US"}]}}}},{"id":"cushion_stonecutvalues","name":"CUSHION","type":"stonecutvalues","domain":"referenceData","properties":{"source":"internal"},"data":{"attributes":{"referencedatacode":{"values":[{"value":"CUSHION","source":"internal","locale":"en-US"}]},"referencedatavalue":{"values":[{"value":"CUSHION","source":"internal","locale":"en-US"}]},"externalName":{"values":[{"value":"CUSHION","source":"internal","locale":"en-US"}]}}}},{"id":"emerald_stonecutvalues","name":"EMERALD","type":"stonecutvalues","domain":"referenceData","properties":{"source":"internal"},"data":{"attributes":{"referencedatacode":{"values":[{"value":"EMERALD","source":"internal","locale":"en-US"}]},"referencedatavalue":{"values":[{"value":"EMERALD","source":"internal","locale":"en-US"}]},"externalName":{"values":[{"value":"EMERALD","source":"internal","locale":"en-US"}]}}}},{"id":"fancy_stonecutvalues","name":"FANCY","type":"stonecutvalues","domain":"referenceData","properties":{"source":"internal"},"data":{"attributes":{"referencedatacode":{"values":[{"value":"FANCY","source":"internal","locale":"en-US"}]},"referencedatavalue":{"values":[{"value":"FANCY","source":"internal","locale":"en-US"}]},"externalName":{"values":[{"value":"FANCY","source":"internal","locale":"en-US"}]}}}},{"id":"heart_stonecutvalues","name":"HEART","type":"stonecutvalues","domain":"referenceData","properties":{"source":"internal"},"data":{"attributes":{"referencedatacode":{"values":[{"value":"HEART","source":"internal","locale":"en-US"}]},"referencedatavalue":{"values":[{"value":"HEART","source":"internal","locale":"en-US"}]},"externalName":{"values":[{"value":"HEART","source":"internal","locale":"en-US"}]}}}},{"id":"lovecut_stonecutvalues","name":"LOVE_CUT","type":"stonecutvalues","domain":"referenceData","properties":{"source":"internal"},"data":{"attributes":{"referencedatacode":{"values":[{"value":"LOVE_CUT","source":"internal","locale":"en-US"}]},"referencedatavalue":{"values":[{"value":"LOVE CUT","source":"internal","locale":"en-US"}]},"externalName":{"values":[{"value":"LOVE CUT","source":"internal","locale":"en-US"}]}}}},{"id":"marquise_stonecutvalues","name":"MARQUISE","type":"stonecutvalues","domain":"referenceData","properties":{"source":"internal"},"data":{"attributes":{"referencedatacode":{"values":[{"value":"MARQUISE","source":"internal","locale":"en-US"}]},"referencedatavalue":{"values":[{"value":"MARQUISE","source":"internal","locale":"en-US"}]},"externalName":{"values":[{"value":"MARQUISE","source":"internal","locale":"en-US"}]}}}},{"id":"multishape_stonecutvalues","name":"MULTI-SHAPE","type":"stonecutvalues","domain":"referenceData","properties":{"source":"internal"},"data":{"attributes":{"referencedatacode":{"values":[{"value":"MULTI-SHAPE","source":"internal","locale":"en-US"}]},"referencedatavalue":{"values":[{"value":"MULTI-SHAPE","source":"internal","locale":"en-US"}]},"externalName":{"values":[{"value":"MULTI-SHAPE","source":"internal","locale":"en-US"}]}}}},{"id":"notapplicable_stonecutvalues","name":"NOT_APPLICABLE","type":"stonecutvalues","domain":"referenceData","properties":{"source":"internal"},"data":{"attributes":{"referencedatacode":{"values":[{"value":"NOT_APPLICABLE","source":"internal","locale":"en-US"}]},"referencedatavalue":{"values":[{"value":"NOT APPLICABLE","source":"internal","locale":"en-US"}]},"externalName":{"values":[{"value":"NOT APPLICABLE","source":"internal","locale":"en-US"}]}}}},{"id":"octagon_stonecutvalues","name":"OCTAGON","type":"stonecutvalues","domain":"referenceData","properties":{"source":"internal"},"data":{"attributes":{"referencedatacode":{"values":[{"value":"OCTAGON","source":"internal","locale":"en-US"}]},"referencedatavalue":{"values":[{"value":"OCTAGON","source":"internal","locale":"en-US"}]},"externalName":{"values":[{"value":"OCTAGON","source":"internal","locale":"en-US"}]}}}},{"id":"oval_stonecutvalues","name":"OVAL","type":"stonecutvalues","domain":"referenceData","properties":{"source":"internal"},"data":{"attributes":{"referencedatacode":{"values":[{"value":"OVAL","source":"internal","locale":"en-US"}]},"referencedatavalue":{"values":[{"value":"OVAL","source":"internal","locale":"en-US"}]},"externalName":{"values":[{"value":"OVAL","source":"internal","locale":"en-US"}]}}}},{"id":"pear_stonecutvalues","name":"PEAR","type":"stonecutvalues","domain":"referenceData","properties":{"source":"internal"},"data":{"attributes":{"referencedatacode":{"values":[{"value":"PEAR","source":"internal","locale":"en-US"}]},"referencedatavalue":{"values":[{"value":"PEAR","source":"internal","locale":"en-US"}]},"externalName":{"values":[{"value":"PEAR","source":"internal","locale":"en-US"}]}}}},{"id":"princess_stonecutvalues","name":"PRINCESS","type":"stonecutvalues","domain":"referenceData","properties":{"source":"internal"},"data":{"attributes":{"referencedatacode":{"values":[{"value":"PRINCESS","source":"internal","locale":"en-US"}]},"referencedatavalue":{"values":[{"value":"PRINCESS","source":"internal","locale":"en-US"}]},"externalName":{"values":[{"value":"PRINCESS","source":"internal","locale":"en-US"}]}}}},{"id":"radiant_stonecutvalues","name":"RADIANT","type":"stonecutvalues","domain":"referenceData","properties":{"source":"internal"},"data":{"attributes":{"referencedatacode":{"values":[{"value":"RADIANT","source":"internal","locale":"en-US"}]},"referencedatavalue":{"values":[{"value":"RADIANT","source":"internal","locale":"en-US"}]},"externalName":{"values":[{"value":"RADIANT","source":"internal","locale":"en-US"}]}}}},{"id":"round_stonecutvalues","name":"ROUND","type":"stonecutvalues","domain":"referenceData","properties":{"source":"internal"},"data":{"attributes":{"referencedatacode":{"values":[{"value":"ROUND","source":"internal","locale":"en-US"}]},"referencedatavalue":{"values":[{"value":"ROUND","source":"internal","locale":"en-US"}]},"externalName":{"values":[{"value":"ROUND","source":"internal","locale":"en-US"}]}}}},{"id":"straightbaguette_stonecutvalues","name":"STRAIGHT_BAGUETTE","type":"stonecutvalues","domain":"referenceData","properties":{"source":"internal"},"data":{"attributes":{"referencedatacode":{"values":[{"value":"STRAIGHT_BAGUETTE","source":"internal","locale":"en-US"}]},"referencedatavalue":{"values":[{"value":"STRAIGHT BAGUETTE","source":"internal","locale":"en-US"}]},"externalName":{"values":[{"value":"STRAIGHT BAGUETTE","source":"internal","locale":"en-US"}]}}}},{"id":"trillion_stonecutvalues","name":"TRILLION","type":"stonecutvalues","domain":"referenceData","properties":{"source":"internal"},"data":{"attributes":{"referencedatacode":{"values":[{"value":"TRILLION","source":"internal","locale":"en-US"}]},"referencedatavalue":{"values":[{"value":"TRILLION","source":"internal","locale":"en-US"}]},"externalName":{"values":[{"value":"TRILLION","source":"internal","locale":"en-US"}]}}}}]}