{"metaInfo":{"dataIndex":"entityData","collectionName":"entities","responseObjectName":"response"},"entities":[{"id":"INCHES","type":"apparellengthvalues","domain":"referenceData","properties":{"source":"internal","modifiedByService":"entityservice","modifiedBy":"initLoad","modifiedDate":"6/1/2017  00:00:00 AM"},"data":{"attributes":{"referencedatacode":{"values":[{"value":"INCHES","source":"internal","locale":"en-US"}]},"referencedatavalue":{"values":[{"value":"INCHES","source":"internal","locale":"en-US"}]}}}},{"id":"NOT_APPLICABLE","type":"apparellengthvalues","domain":"referenceData","properties":{"source":"internal","modifiedByService":"entityservice","modifiedBy":"initLoad","modifiedDate":"6/1/2017  00:00:00 AM"},"data":{"attributes":{"referencedatacode":{"values":[{"value":"NOT_APPLICABLE","source":"internal","locale":"en-US"}]},"referencedatavalue":{"values":[{"value":"NOT APPLICABLE","source":"internal","locale":"en-US"}]}}}}]}