{"metaInfo":{"dataIndex":"entityData","collectionName":"entities","responseObjectName":"response"},"entities":[{"id":"AUTO_BLEACH_washerdispensersvalues","name":"AUTO_BLEACH","type":"washerdispensersvalues","domain":"referenceData","properties":{"source":"internal","modifiedByService":"entityservice","modifiedBy":"initLoad","modifiedDate":"6/1/2017  00:00:00 AM"},"data":{"attributes":{"referencedatacode":{"values":[{"value":"AUTO_BLEACH","source":"internal","locale":"en-US"}]},"referencedatavalue":{"values":[{"value":"AUTO BLEACH","source":"internal","locale":"en-US"}]}}}},{"id":"AUTO_DETERGENT_washerdispensersvalues","name":"AUTO_DETERGENT","type":"washerdispensersvalues","domain":"referenceData","properties":{"source":"internal","modifiedByService":"entityservice","modifiedBy":"initLoad","modifiedDate":"6/1/2017  00:00:00 AM"},"data":{"attributes":{"referencedatacode":{"values":[{"value":"AUTO_DETERGENT","source":"internal","locale":"en-US"}]},"referencedatavalue":{"values":[{"value":"AUTO DETERGENT","source":"internal","locale":"en-US"}]}}}},{"id":"AUTO_FABRIC_SOFTENER_washerdispensersvalues","name":"AUTO_FABRIC_SOFTENER","type":"washerdispensersvalues","domain":"referenceData","properties":{"source":"internal","modifiedByService":"entityservice","modifiedBy":"initLoad","modifiedDate":"6/1/2017  00:00:00 AM"},"data":{"attributes":{"referencedatacode":{"values":[{"value":"AUTO_FABRIC_SOFTENER","source":"internal","locale":"en-US"}]},"referencedatavalue":{"values":[{"value":"AUTO FABRIC SOFTENER","source":"internal","locale":"en-US"}]}}}},{"id":"BLEACH_washerdispensersvalues","name":"BLEACH","type":"washerdispensersvalues","domain":"referenceData","properties":{"source":"internal","modifiedByService":"entityservice","modifiedBy":"initLoad","modifiedDate":"6/1/2017  00:00:00 AM"},"data":{"attributes":{"referencedatacode":{"values":[{"value":"BLEACH","source":"internal","locale":"en-US"}]},"referencedatavalue":{"values":[{"value":"BLEACH","source":"internal","locale":"en-US"}]}}}},{"id":"DETERGENT_LIQUID_washerdispensersvalues","name":"DETERGENT_LIQUID","type":"washerdispensersvalues","domain":"referenceData","properties":{"source":"internal","modifiedByService":"entityservice","modifiedBy":"initLoad","modifiedDate":"6/1/2017  00:00:00 AM"},"data":{"attributes":{"referencedatacode":{"values":[{"value":"DETERGENT_LIQUID","source":"internal","locale":"en-US"}]},"referencedatavalue":{"values":[{"value":"DETERGENT LIQUID","source":"internal","locale":"en-US"}]}}}},{"id":"DETERGENT_POWDER_washerdispensersvalues","name":"DETERGENT_POWDER","type":"washerdispensersvalues","domain":"referenceData","properties":{"source":"internal","modifiedByService":"entityservice","modifiedBy":"initLoad","modifiedDate":"6/1/2017  00:00:00 AM"},"data":{"attributes":{"referencedatacode":{"values":[{"value":"DETERGENT_POWDER","source":"internal","locale":"en-US"}]},"referencedatavalue":{"values":[{"value":"DETERGENT POWDER","source":"internal","locale":"en-US"}]}}}},{"id":"FABRIC_SOFTENER_washerdispensersvalues","name":"FABRIC_SOFTENER","type":"washerdispensersvalues","domain":"referenceData","properties":{"source":"internal","modifiedByService":"entityservice","modifiedBy":"initLoad","modifiedDate":"6/1/2017  00:00:00 AM"},"data":{"attributes":{"referencedatacode":{"values":[{"value":"FABRIC_SOFTENER","source":"internal","locale":"en-US"}]},"referencedatavalue":{"values":[{"value":"FABRIC SOFTENER","source":"internal","locale":"en-US"}]}}}},{"id":"NOT_APPLICABLE_washerdispensersvalues","name":"NOT_APPLICABLE","type":"washerdispensersvalues","domain":"referenceData","properties":{"source":"internal","modifiedByService":"entityservice","modifiedBy":"initLoad","modifiedDate":"6/1/2017  00:00:00 AM"},"data":{"attributes":{"referencedatacode":{"values":[{"value":"NOT_APPLICABLE","source":"internal","locale":"en-US"}]},"referencedatavalue":{"values":[{"value":"NOT APPLICABLE","source":"internal","locale":"en-US"}]}}}},{"id":"PRETREAT_washerdispensersvalues","name":"PRETREAT","type":"washerdispensersvalues","domain":"referenceData","properties":{"source":"internal","modifiedByService":"entityservice","modifiedBy":"initLoad","modifiedDate":"6/1/2017  00:00:00 AM"},"data":{"attributes":{"referencedatacode":{"values":[{"value":"PRETREAT","source":"internal","locale":"en-US"}]},"referencedatavalue":{"values":[{"value":"PRETREAT","source":"internal","locale":"en-US"}]}}}},{"id":"PREWASH_washerdispensersvalues","name":"PREWASH","type":"washerdispensersvalues","domain":"referenceData","properties":{"source":"internal","modifiedByService":"entityservice","modifiedBy":"initLoad","modifiedDate":"6/1/2017  00:00:00 AM"},"data":{"attributes":{"referencedatacode":{"values":[{"value":"PREWASH","source":"internal","locale":"en-US"}]},"referencedatavalue":{"values":[{"value":"PREWASH","source":"internal","locale":"en-US"}]}}}},{"id":"SMARTDISPENSE_washerdispensersvalues","name":"SMARTDISPENSE","type":"washerdispensersvalues","domain":"referenceData","properties":{"source":"internal","modifiedByService":"entityservice","modifiedBy":"initLoad","modifiedDate":"6/1/2017  00:00:00 AM"},"data":{"attributes":{"referencedatacode":{"values":[{"value":"SMARTDISPENSE","source":"internal","locale":"en-US"}]},"referencedatavalue":{"values":[{"value":"SMARTDISPENSE","source":"internal","locale":"en-US"}]}}}}]}