{"metaInfo":{"dataIndex":"entityData","collectionName":"entities","responseObjectName":"response"},"entities":[{"id":"dreamcast_videogamesystemvalues","name":"DREAMCAST","type":"videogamesystemvalues","domain":"referenceData","properties":{"source":"internal","modifiedByService":"entityservice","modifiedBy":"initLoad","modifiedDate":"6/1/2017  00:00:00 AM"},"data":{"attributes":{"referencedatacode":{"values":[{"value":"DREAMCAST","source":"internal","locale":"en-US"}]},"referencedatavalue":{"values":[{"value":"DREAMCAST","source":"internal","locale":"en-US"}]},"externalName":{"values":[{"value":"DREAMCAST","source":"internal","locale":"en-US"}]}}}},{"id":"gamecube_videogamesystemvalues","name":"GAME_CUBE","type":"videogamesystemvalues","domain":"referenceData","properties":{"source":"internal","modifiedByService":"entityservice","modifiedBy":"initLoad","modifiedDate":"6/1/2017  00:00:00 AM"},"data":{"attributes":{"referencedatacode":{"values":[{"value":"GAME_CUBE","source":"internal","locale":"en-US"}]},"referencedatavalue":{"values":[{"value":"GAME CUBE","source":"internal","locale":"en-US"}]},"externalName":{"values":[{"value":"GAME CUBE","source":"internal","locale":"en-US"}]}}}},{"id":"neogeox_videogamesystemvalues","name":"NEO_GEO_X","type":"videogamesystemvalues","domain":"referenceData","properties":{"source":"internal","modifiedByService":"entityservice","modifiedBy":"initLoad","modifiedDate":"6/1/2017  00:00:00 AM"},"data":{"attributes":{"referencedatacode":{"values":[{"value":"NEO_GEO_X","source":"internal","locale":"en-US"}]},"referencedatavalue":{"values":[{"value":"NEO GEO X","source":"internal","locale":"en-US"}]},"externalName":{"values":[{"value":"NEO GEO X","source":"internal","locale":"en-US"}]}}}},{"id":"nintendo_videogamesystemvalues","name":"NINTENDO","type":"videogamesystemvalues","domain":"referenceData","properties":{"source":"internal","modifiedByService":"entityservice","modifiedBy":"initLoad","modifiedDate":"6/1/2017  00:00:00 AM"},"data":{"attributes":{"referencedatacode":{"values":[{"value":"NINTENDO","source":"internal","locale":"en-US"}]},"referencedatavalue":{"values":[{"value":"NINTENDO","source":"internal","locale":"en-US"}]},"externalName":{"values":[{"value":"NINTENDO","source":"internal","locale":"en-US"}]}}}},{"id":"nintendo2ds_videogamesystemvalues","name":"NINTENDO_2DS","type":"videogamesystemvalues","domain":"referenceData","properties":{"source":"internal","modifiedByService":"entityservice","modifiedBy":"initLoad","modifiedDate":"6/1/2017  00:00:00 AM"},"data":{"attributes":{"referencedatacode":{"values":[{"value":"NINTENDO_2DS","source":"internal","locale":"en-US"}]},"referencedatavalue":{"values":[{"value":"NINTENDO 2DS","source":"internal","locale":"en-US"}]},"externalName":{"values":[{"value":"NINTENDO 2DS","source":"internal","locale":"en-US"}]}}}},{"id":"nintendo3ds_videogamesystemvalues","name":"NINTENDO_3DS","type":"videogamesystemvalues","domain":"referenceData","properties":{"source":"internal","modifiedByService":"entityservice","modifiedBy":"initLoad","modifiedDate":"6/1/2017  00:00:00 AM"},"data":{"attributes":{"referencedatacode":{"values":[{"value":"NINTENDO_3DS","source":"internal","locale":"en-US"}]},"referencedatavalue":{"values":[{"value":"NINTENDO 3DS","source":"internal","locale":"en-US"}]},"externalName":{"values":[{"value":"NINTENDO 3DS","source":"internal","locale":"en-US"}]}}}},{"id":"nintendo3dsxl_videogamesystemvalues","name":"NINTENDO_3DS_XL","type":"videogamesystemvalues","domain":"referenceData","properties":{"source":"internal","modifiedByService":"entityservice","modifiedBy":"initLoad","modifiedDate":"6/1/2017  00:00:00 AM"},"data":{"attributes":{"referencedatacode":{"values":[{"value":"NINTENDO_3DS_XL","source":"internal","locale":"en-US"}]},"referencedatavalue":{"values":[{"value":"NINTENDO 3DS XL","source":"internal","locale":"en-US"}]},"externalName":{"values":[{"value":"NINTENDO 3DS XL","source":"internal","locale":"en-US"}]}}}},{"id":"nintendods_videogamesystemvalues","name":"NINTENDO_DS","type":"videogamesystemvalues","domain":"referenceData","properties":{"source":"internal","modifiedByService":"entityservice","modifiedBy":"initLoad","modifiedDate":"6/1/2017  00:00:00 AM"},"data":{"attributes":{"referencedatacode":{"values":[{"value":"NINTENDO_DS","source":"internal","locale":"en-US"}]},"referencedatavalue":{"values":[{"value":"NINTENDO DS","source":"internal","locale":"en-US"}]},"externalName":{"values":[{"value":"NINTENDO DS","source":"internal","locale":"en-US"}]}}}},{"id":"nintendogamecube_videogamesystemvalues","name":"NINTENDO_GAME_CUBE","type":"videogamesystemvalues","domain":"referenceData","properties":{"source":"internal","modifiedByService":"entityservice","modifiedBy":"initLoad","modifiedDate":"6/1/2017  00:00:00 AM"},"data":{"attributes":{"referencedatacode":{"values":[{"value":"NINTENDO_GAME_CUBE","source":"internal","locale":"en-US"}]},"referencedatavalue":{"values":[{"value":"NINTENDO GAME CUBE","source":"internal","locale":"en-US"}]},"externalName":{"values":[{"value":"NINTENDO GAME CUBE","source":"internal","locale":"en-US"}]}}}},{"id":"notapplicable_videogamesystemvalues","name":"NOT_APPLICABLE","type":"videogamesystemvalues","domain":"referenceData","properties":{"source":"internal","modifiedByService":"entityservice","modifiedBy":"initLoad","modifiedDate":"6/1/2017  00:00:00 AM"},"data":{"attributes":{"referencedatacode":{"values":[{"value":"NOT_APPLICABLE","source":"internal","locale":"en-US"}]},"referencedatavalue":{"values":[{"value":"NOT APPLICABLE","source":"internal","locale":"en-US"}]},"externalName":{"values":[{"value":"NOT APPLICABLE","source":"internal","locale":"en-US"}]}}}},{"id":"playstation2_videogamesystemvalues","name":"PLAYSTATION_2","type":"videogamesystemvalues","domain":"referenceData","properties":{"source":"internal","modifiedByService":"entityservice","modifiedBy":"initLoad","modifiedDate":"6/1/2017  00:00:00 AM"},"data":{"attributes":{"referencedatacode":{"values":[{"value":"PLAYSTATION_2","source":"internal","locale":"en-US"}]},"referencedatavalue":{"values":[{"value":"PLAYSTATION 2","source":"internal","locale":"en-US"}]},"externalName":{"values":[{"value":"PLAYSTATION 2","source":"internal","locale":"en-US"}]}}}},{"id":"playstation3_videogamesystemvalues","name":"PLAYSTATION_3","type":"videogamesystemvalues","domain":"referenceData","properties":{"source":"internal","modifiedByService":"entityservice","modifiedBy":"initLoad","modifiedDate":"6/1/2017  00:00:00 AM"},"data":{"attributes":{"referencedatacode":{"values":[{"value":"PLAYSTATION_3","source":"internal","locale":"en-US"}]},"referencedatavalue":{"values":[{"value":"PLAYSTATION 3","source":"internal","locale":"en-US"}]},"externalName":{"values":[{"value":"PLAYSTATION 3","source":"internal","locale":"en-US"}]}}}},{"id":"playstation4_videogamesystemvalues","name":"PLAYSTATION_4","type":"videogamesystemvalues","domain":"referenceData","properties":{"source":"internal","modifiedByService":"entityservice","modifiedBy":"initLoad","modifiedDate":"6/1/2017  00:00:00 AM"},"data":{"attributes":{"referencedatacode":{"values":[{"value":"PLAYSTATION_4","source":"internal","locale":"en-US"}]},"referencedatavalue":{"values":[{"value":"PLAYSTATION 4","source":"internal","locale":"en-US"}]},"externalName":{"values":[{"value":"PLAYSTATION 4","source":"internal","locale":"en-US"}]}}}},{"id":"playstationvita_videogamesystemvalues","name":"PLAYSTATION_VITA","type":"videogamesystemvalues","domain":"referenceData","properties":{"source":"internal","modifiedByService":"entityservice","modifiedBy":"initLoad","modifiedDate":"6/1/2017  00:00:00 AM"},"data":{"attributes":{"referencedatacode":{"values":[{"value":"PLAYSTATION_VITA","source":"internal","locale":"en-US"}]},"referencedatavalue":{"values":[{"value":"PLAYSTATION VITA","source":"internal","locale":"en-US"}]},"externalName":{"values":[{"value":"PLAYSTATION VITA","source":"internal","locale":"en-US"}]}}}},{"id":"ps2_videogamesystemvalues","name":"PS2","type":"videogamesystemvalues","domain":"referenceData","properties":{"source":"internal","modifiedByService":"entityservice","modifiedBy":"initLoad","modifiedDate":"6/1/2017  00:00:00 AM"},"data":{"attributes":{"referencedatacode":{"values":[{"value":"PS2","source":"internal","locale":"en-US"}]},"referencedatavalue":{"values":[{"value":"PS2","source":"internal","locale":"en-US"}]},"externalName":{"values":[{"value":"PS2","source":"internal","locale":"en-US"}]}}}},{"id":"ps3_videogamesystemvalues","name":"PS3","type":"videogamesystemvalues","domain":"referenceData","properties":{"source":"internal","modifiedByService":"entityservice","modifiedBy":"initLoad","modifiedDate":"6/1/2017  00:00:00 AM"},"data":{"attributes":{"referencedatacode":{"values":[{"value":"PS3","source":"internal","locale":"en-US"}]},"referencedatavalue":{"values":[{"value":"PS3","source":"internal","locale":"en-US"}]},"externalName":{"values":[{"value":"PS3","source":"internal","locale":"en-US"}]}}}},{"id":"psp_videogamesystemvalues","name":"PSP","type":"videogamesystemvalues","domain":"referenceData","properties":{"source":"internal","modifiedByService":"entityservice","modifiedBy":"initLoad","modifiedDate":"6/1/2017  00:00:00 AM"},"data":{"attributes":{"referencedatacode":{"values":[{"value":"PSP","source":"internal","locale":"en-US"}]},"referencedatavalue":{"values":[{"value":"PSP","source":"internal","locale":"en-US"}]},"externalName":{"values":[{"value":"PSP","source":"internal","locale":"en-US"}]}}}},{"id":"wii_videogamesystemvalues","name":"WII","type":"videogamesystemvalues","domain":"referenceData","properties":{"source":"internal","modifiedByService":"entityservice","modifiedBy":"initLoad","modifiedDate":"6/1/2017  00:00:00 AM"},"data":{"attributes":{"referencedatacode":{"values":[{"value":"WII","source":"internal","locale":"en-US"}]},"referencedatavalue":{"values":[{"value":"WII","source":"internal","locale":"en-US"}]},"externalName":{"values":[{"value":"WII","source":"internal","locale":"en-US"}]}}}},{"id":"wiiu_videogamesystemvalues","name":"WII_U","type":"videogamesystemvalues","domain":"referenceData","properties":{"source":"internal","modifiedByService":"entityservice","modifiedBy":"initLoad","modifiedDate":"6/1/2017  00:00:00 AM"},"data":{"attributes":{"referencedatacode":{"values":[{"value":"WII_U","source":"internal","locale":"en-US"}]},"referencedatavalue":{"values":[{"value":"WII U","source":"internal","locale":"en-US"}]},"externalName":{"values":[{"value":"WII U","source":"internal","locale":"en-US"}]}}}},{"id":"xbox_videogamesystemvalues","name":"XBOX","type":"videogamesystemvalues","domain":"referenceData","properties":{"source":"internal","modifiedByService":"entityservice","modifiedBy":"initLoad","modifiedDate":"6/1/2017  00:00:00 AM"},"data":{"attributes":{"referencedatacode":{"values":[{"value":"XBOX","source":"internal","locale":"en-US"}]},"referencedatavalue":{"values":[{"value":"XBOX","source":"internal","locale":"en-US"}]},"externalName":{"values":[{"value":"XBOX","source":"internal","locale":"en-US"}]}}}},{"id":"xbox360_videogamesystemvalues","name":"XBOX_360","type":"videogamesystemvalues","domain":"referenceData","properties":{"source":"internal","modifiedByService":"entityservice","modifiedBy":"initLoad","modifiedDate":"6/1/2017  00:00:00 AM"},"data":{"attributes":{"referencedatacode":{"values":[{"value":"XBOX_360","source":"internal","locale":"en-US"}]},"referencedatavalue":{"values":[{"value":"XBOX 360","source":"internal","locale":"en-US"}]},"externalName":{"values":[{"value":"XBOX 360","source":"internal","locale":"en-US"}]}}}},{"id":"xboxone_videogamesystemvalues","name":"XBOX_ONE","type":"videogamesystemvalues","domain":"referenceData","properties":{"source":"internal","modifiedByService":"entityservice","modifiedBy":"initLoad","modifiedDate":"6/1/2017  00:00:00 AM"},"data":{"attributes":{"referencedatacode":{"values":[{"value":"XBOX_ONE","source":"internal","locale":"en-US"}]},"referencedatavalue":{"values":[{"value":"XBOX ONE","source":"internal","locale":"en-US"}]},"externalName":{"values":[{"value":"XBOX ONE","source":"internal","locale":"en-US"}]}}}},{"id":"xboxones_videogamesystemvalues","name":"XBOX_ONE_S","type":"videogamesystemvalues","domain":"referenceData","properties":{"source":"internal","modifiedByService":"entityservice","modifiedBy":"initLoad","modifiedDate":"6/1/2017  00:00:00 AM"},"data":{"attributes":{"referencedatacode":{"values":[{"value":"XBOX_ONE_S","source":"internal","locale":"en-US"}]},"referencedatavalue":{"values":[{"value":"XBOX ONE S","source":"internal","locale":"en-US"}]},"externalName":{"values":[{"value":"XBOX ONE S","source":"internal","locale":"en-US"}]}}}}]}